{
	"translations": {
		"de": {
			"Instance is disabled": "Instanz ist deaktiviert",

			"Netatmo Access-Details": "Netatmo Zugangsdaten",

			"Netatmo-Account from https://my.netatmo.com":
				"Netatmo Konto-Daten von https://my.netatmo.com",
			"Username": "Benutzername",
			"Password": "Passwort",

			"Netatmo-Connect from https://dev.netatmo.com":
				"Netatmo-Connect-Daten von https://dev.netatmo.com",
			"Client ID": "Client ID",
			"Client Secret": "Client Secret",

			"Ignore HTTP-Error X times": "HTTP-Fehler X-fach ignorieren",
			"Count": "Anzahl",

			"Update weatherdata every X minutes": "Aktualisiere Wetterdaten alle X Minuten",
			"Minutes": "Minuten",

			"Update weatherdata": "Aktualisiere Wetterdaten",

			"Module description": "Modulbeschreibung",

			"Instance getting created": "Instanz wird erstellt",
			"Instance is active": "Instanz ist aktiv",
			"Instance is deleted": "Instanz wird gelöscht",
			"Instance is inactive": "Instanz ist inaktiv",
			"Instance is not created": "Instanz wurde nicht erzeugt",

			"Instance is inactive (no data)": "Instanz ist inaktiv (keine Daten)",
			"Instance is inactive (unauthorized)": "Instanz ist inaktiv (Authorisierung fehlerhaft)",
			"Instance is inactive (server error)": "Instanz ist inaktiv (Serverfehler)",
			"Instance is inactive (http error)": "Instanz ist inaktiv (HTTP-Fehler)",
			"Instance is inactive (invalid data)": "Instanz ist inaktiv (ungültige Daten)",
			"Instance is inactive (no station)": "Instanz ist inaktiv (keine Station)",
			"Instance is inactive (station missing)": "Instanz ist inaktiv (Station ist unbekannt)"
		}
	}
}
